Workbook

Sheet README
A1: European FBO & Ground Handling — Market Research
A3: Purpose | B3: Identify regional and independent FBOs and ground handlers across European secondary hubs as potential customers for a flight operations dashboard platform.
A4: Scope | B4: Excludes the global mega-handlers (Menzies, Swissport, dnata, WFS-cargo) from the prospecting focus, but they are noted where they are the only operator at an airport, so you know the competitive landscape.
A5: Source date | B5: Research compiled April 2026 from public sources: AENA, airport B2B portals, company websites, trade press (Regional Gateway, AIN, Business Air News), CAPA, LinkedIn.
A7: Column guide
A8: Type | B8: FBO = business/private aviation terminal operator. Handler = commercial airline ground handler. Both = operates in both segments.
A9: Segment | B9: Biz Av = business aviation focus. Commercial = scheduled airline handling. Cargo = freight handling. Mixed = more than one.
A10: Employees | B10: Approximate, from public sources. Blank where no reliable public figure exists.
A11: Modernization signal | B11: INFERRED from public signals only — tech press releases, ISO certifications, visible digital tooling, recent equipment investment, IS-BAH accreditation. NOT a verified audit. Use as a starting hypothesis for qualification calls, not as ground truth.
A12: Modern | B12: Clear digital / recent tech investment signals (e.g., IS-BAH Stage 2, published ISO 27001, own ops apps, recent GSE electrification).
A13: Mixed | B13: Established operator with some modernization signals but likely still mixed workflows.
A14: Traditional | B14: Few public modernization signals. Likely candidate for digital transformation — often the most interesting prospect.
A15: Unknown | B15: Not enough public info to assess.
A17: Prospecting tip | B17: The 'Traditional' and 'Mixed' rows are usually the highest-value prospects for a dashboard product. 'Modern' operators may already have an internal solution or a competitor product. Regional independents (G.A.S. Spain, GH Italia, Goldair, Portway, Sky Valet Connect affiliates) are the sweet spot — large enough to have budget, small enough to buy without a 12-month procurement cycle.
A19: Important caveat | B19: Aena's 2023 handling tender reshuffled Spanish licenses effective April 2024. Aviapartner gained Madrid, Barcelona, Valencia, Alicante, Ibiza, Bilbao. IAG formed 'South Europe Ground Services' (South) covering 38 airports. Data reflects the post-2024 landscape where verifiable; some sources predate it and are noted.

Sheet FBO & Handler Directory
A1: Country | B1: City | C1: Airport | D1: ICAO | E1: IATA | F1: Company | G1: Type | H1: Segment focus | I1: Parent / Network | J1: Approx. employees | K1: Modernization signal | L1: Notes | M1: Priority (you fill)
A2: Spain | B2: Madrid | C2: Adolfo Suárez Madrid-Barajas | D2: LEMD | E2: MAD | F2: General Aviation Service (G.A.S.) | G2: FBO | H2: Biz Av | I2: Independent (family-owned, since 1979) | J2: ~100 (group-wide) | K2: Modern | L2: Nine-base Spanish FBO network. Invested €200k in new handling equipment in early 2025; first GA handler in Spain authorised to operate TowFLEXX TF5 electric tugs. Flagship independent.
A3: Spain | B3: Madrid | C3: Adolfo Suárez Madrid-Barajas | D3: LEMD | E3: MAD | F3: South Europe Ground Services (South) | G3: Handler | H3: Commercial | I3: IAG Group (Iberia spin-off) | J3: ~8,700 | K3: Mixed | L3: Formed 2024 from Iberia Airport Services. Present at 38 Spanish airports. New entity — internal systems likely inherited from Iberia, being restructured; possible greenfield for new tooling.
A4: Spain | B4: Madrid | C4: Adolfo Suárez Madrid-Barajas | D4: LEMD | E4: MAD | F4: WFS (Worldwide Flight Services) | G4: Handler | H4: Cargo + Commercial | I4: Platinum Equity / SATS | J4: Not disclosed (Spain) | K4: Mixed | L4: Cargo leader in MAD, BCN, VLC, BIO. Added full passenger/ramp in Madrid + Seville 2023. Global group, but Spain is a discrete P&L — worth approaching at country-manager level.
A5: Spain | B5: Madrid | C5: Adolfo Suárez Madrid-Barajas | D5: LEMD | E5: MAD | F5: Sky Valet Spain | G5: FBO | H5: Biz Av | I5: Aéroports de la Côte d'Azur (ACA) | J5: Not disclosed | K5: Modern | L5: Part of 45-FBO pan-European network. Centralised OCC in Spain at +34 916 782 648. Likely has internal tools but satellite bases may operate semi-independently.
A6: Spain | B6: Barcelona | C6: Barcelona–El Prat | D6: LEBL | E6: BCN | F6: General Aviation Service (G.A.S.) | G6: FBO | H6: Biz Av | I6: Independent | J6: Part of ~100 group | K6: Modern | L6: TowFLEXX electric tug already deployed here. Strong biz av hub — F1, Mobile World Congress peaks.
A7: Spain | B7: Barcelona | C7: Barcelona–El Prat | D7: LEBL | E7: BCN | F7: ExecuJet Barcelona | G7: FBO | H7: Biz Av | I7: Luxaviation Group | J7: Not disclosed | K7: Modern | L7: One of four ExecuJet Spanish FBOs (BCN, GRO, IBZ, VLC). Spanish HQ in Palma. Global group tools.
A8: Spain | B8: Barcelona | C8: Barcelona–El Prat | D8: LEBL | E8: BCN | F8: Sky Valet Barcelona | G8: FBO | H8: Biz Av | I8: Aéroports de la Côte d'Azur | J8: Not disclosed | K8: Modern | L8: ACA network base.
A9: Spain | B9: Valencia | C9: Valencia Airport (Manises) | D9: LEVC | E9: VLC | F9: General Aviation Service (G.A.S.) | G9: FBO | H9: Biz Av | I9: Independent | J9: Part of ~100 group | K9: Modern | L9: Valencia Airport, Edificio Bloque Técnico. Terminal Aviación General.
A10: Spain | B10: Valencia | C10: Valencia Airport (Manises) | D10: LEVC | E10: VLC | F10: ExecuJet Valencia | G10: FBO | H10: Biz Av | I10: Luxaviation | J10: Not disclosed | K10: Modern
A11: Spain | B11: Valencia | C11: Valencia Airport (Manises) | D11: LEVC | E11: VLC | F11: Sky Valet Valencia | G11: FBO | H11: Biz Av | I11: ACA | J11: Not disclosed | K11: Modern
A12: Spain | B12: Valencia | C12: Valencia Airport (Manises) | D12: LEVC | E12: VLC | F12: Aviapartner Valencia | G12: Handler | H12: Commercial | I12: Aviapartner (Belgian independent) | J12: Part of ~12,000 group | K12: Mixed | L12: Won license in 2023 Aena tender, effective April 2024. Committed to full GSE electrification — modernisation in progress, good timing for dashboard pitch.
A13: Spain | B13: Bilbao | C13: Bilbao Airport | D13: LEBB | E13: BIO | F13: Aviapartner Bilbao | G13: Handler | H13: Commercial | I13: Aviapartner | J13: Part of ~12,000 group | K13: Mixed | L13: New 2024 license. Aviapartner is actively modernising fleet; central ops may still be handler-oriented rather than biz-av.
A14: Spain | B14: Bilbao | C14: Bilbao Airport | D14: LEBB | E14: BIO | F14: Groundforce Bilbao | G14: Handler | H14: Commercial | I14: Globalia (Spanish group) | J14: Part of Groundforce group (~5,000+) | K14: Traditional | L14: Groundforce is the legacy #2 handler in Spain. Labour-intensive, pre-digital culture at many stations — strong prospect for operational dashboard tooling.
A15: Spain | B15: Bilbao | C15: Bilbao Airport | D15: LEBB | E15: BIO | F15: WFS Bilbao | G15: Handler | H15: Cargo | I15: WFS/Platinum Equity | J15: Not disclosed | K15: Mixed | L15: WFS is the largest cargo handler in Bilbao per company statement.
A16: Spain | B16: Palma de Mallorca | C16: Palma de Mallorca Airport | D16: LEPA | E16: PMI | F16: Mallorcair | G16: FBO | H16: Biz Av | I16: Independent | J16: Not disclosed | K16: Modern | L16: Awarded FBO1 Executive Terminal contract. EMEA Top 10 FBO (Business Air News). Strong local brand — hottest island for biz av in Europe.
A17: Spain | B17: Palma de Mallorca | C17: Palma de Mallorca Airport | D17: LEPA | E17: PMI | F17: General Aviation Service (G.A.S.) | G17: FBO | H17: Biz Av | I17: Independent | J17: Part of ~100 group | K17: Modern | L17: Terminal Ejecutiva. Station Mgr: Sebastia Godia Ozonas.
A18: Spain | B18: Palma de Mallorca | C18: Palma de Mallorca Airport | D18: LEPA | E18: PMI | F18: ExecuJet Palma (Spanish HQ) | G18: FBO | H18: Biz Av | I18: Luxaviation | J18: Not disclosed | K18: Modern | L18: Headquarters for ExecuJet's four Spanish FBOs.
A19: Spain | B19: Palma de Mallorca | C19: Palma de Mallorca Airport | D19: LEPA | E19: PMI | F19: Sky Valet Palma | G19: FBO | H19: Biz Av | I19: ACA | J19: Not disclosed | K19: Modern
A20: Spain | B20: Palma de Mallorca | C20: Palma de Mallorca Airport | D20: LEPA | E20: PMI | F20: AviaVIP Palma | G20: FBO | H20: Biz Av | I20: AviaVIP (regional group) | J20: Not disclosed | K20: Mixed | L20: Also present in Málaga. Smaller player — good early-adopter profile.
A21: Spain | B21: Palma de Mallorca | C21: Palma de Mallorca Airport | D21: LEPA | E21: PMI | F21: South Europe Ground Services (South) | G21: Handler | H21: Commercial | I21: IAG | J21: Part of ~8,700 | K21: Mixed | L21: PMI is a South network node.
A22: Spain | B22: Ibiza | C22: Ibiza Airport | D22: LEIB | E22: IBZ | F22: General Aviation Service (G.A.S.) | G22: FBO | H22: Biz Av | I22: Independent | J22: Part of ~100 group | K22: Modern
A23: Spain | B23: Ibiza | C23: Ibiza Airport | D23: LEIB | E23: IBZ | F23: ExecuJet Ibiza | G23: FBO | H23: Biz Av | I23: Luxaviation | J23: ~4+ local | K23: Modern | L23: IS-BAH Stage 2 accredited, opened 2011 (took over from Assistair). 24h operations. Summer-peaked — ops intensity spikes hugely Jun-Sep.
A24: Spain | B24: Ibiza | C24: Ibiza Airport | D24: LEIB | E24: IBZ | F24: Sky Valet Ibiza | G24: FBO | H24: Biz Av | I24: ACA | J24: Not disclosed | K24: Modern
A25: Spain | B25: Ibiza | C25: Ibiza Airport | D25: LEIB | E25: IBZ | F25: Aviapartner Ibiza | G25: Handler | H25: Commercial | I25: Aviapartner | J25: Part of ~12,000 | K25: Mixed | L25: New 2024 license.
A26: Spain | B26: Málaga | C26: Málaga–Costa del Sol Airport | D26: LEMG | E26: AGP | F26: General Aviation Service (G.A.S.) | G26: FBO | H26: Biz Av | I26: Independent | J26: Part of ~100 group | K26: Modern
A27: Spain | B27: Málaga | C27: Málaga–Costa del Sol Airport | D27: LEMG | E27: AGP | F27: Aviapartner Málaga FBO | G27: FBO + Handler | H27: Biz Av + Commercial | I27: Aviapartner | J27: Part of ~12,000 | K27: Mixed | L27: Separate Málaga FBO S.A. entity. Handler since 2015. GSE electrification commitment under new license.
A28: Spain | B28: Málaga | C28: Málaga–Costa del Sol Airport | D28: LEMG | E28: AGP | F28: AviaVIP Málaga | G28: FBO | H28: Biz Av | I28: AviaVIP | J28: Not disclosed | K28: Mixed | L28: +34 661 829 722. Good smaller-operator prospect.
A29: Spain | B29: Málaga | C29: Málaga–Costa del Sol Airport | D29: LEMG | E29: AGP | F29: Sky Valet Málaga | G29: FBO | H29: Biz Av | I29: ACA | J29: Not disclosed | K29: Modern
A30: Spain | B30: Málaga | C30: Málaga–Costa del Sol Airport | D30: LEMG | E30: AGP | F30: Jetex Málaga | G30: FBO | H30: Biz Av | I30: Jetex (UAE-based) | J30: Not disclosed | K30: Modern | L30: Global group with own proprietary ops platform.
A31: Spain | B31: Alicante | C31: Alicante-Elche | D31: LEAL | E31: ALC | F31: General Aviation Service (G.A.S.) | G31: FBO | H31: Biz Av | I31: Independent | J31: Part of ~100 group | K31: Modern | L31: Station Mgr: Víctor San Román Zabala. First Spanish GA handler authorised for TowFLEXX TF5.
A32: Spain | B32: Alicante | C32: Alicante-Elche | D32: LEAL | E32: ALC | F32: Aviapartner Alicante | G32: Handler | H32: Commercial | I32: Aviapartner | J32: Part of ~12,000 | K32: Mixed
A33: Spain | B33: Girona | C33: Girona-Costa Brava | D33: LEGE | E33: GRO | F33: General Aviation Service (G.A.S.) | G33: FBO | H33: Biz Av | I33: Independent | J33: Part of ~100 group | K33: Modern
A34: Spain | B34: Girona | C34: Girona-Costa Brava | D34: LEGE | E34: GRO | F34: ExecuJet Girona | G34: FBO | H34: Biz Av | I34: Luxaviation | J34: Not disclosed | K34: Modern
A35: Spain | B35: Girona | C35: Girona-Costa Brava | D35: LEGE | E35: GRO | F35: Sky Valet Girona | G35: FBO | H35: Biz Av | I35: ACA | J35: Not disclosed | K35: Modern
A36: Spain | B36: Granada | C36: FGL Granada Jaén | D36: LEGR | E36: GRX | F36: General Aviation Service (G.A.S.) | G36: FBO | H36: Biz Av | I36: Independent | J36: Part of ~100 group | K36: Modern
A37: Spain | B37: Santiago de Compostela | C37: Santiago-Rosalía de Castro | D37: LEST | E37: SCQ | F37: Sky Valet Santiago | G37: FBO | H37: Biz Av | I37: ACA | J37: Not disclosed | K37: Modern
A38: Spain | B38: Santiago de Compostela | C38: Santiago-Rosalía de Castro | D38: LEST | E38: SCQ | F38: WFS Santiago | G38: Handler | H38: Commercial + Cargo | I38: WFS | J38: Not disclosed | K38: Mixed | L38: New from 2023 license round.
A39: Spain | B39: A Coruña | C39: A Coruña Airport | D39: LECO | E39: LCG | F39: Sky Valet A Coruña | G39: FBO | H39: Biz Av | I39: ACA | J39: Not disclosed | K39: Modern
A40: Spain | B40: Seville | C40: Seville Airport | D40: LEZL | E40: SVQ | F40: WFS Seville | G40: Handler | H40: Commercial + Cargo | I40: WFS | J40: Not disclosed | K40: Mixed | L40: Won 2023 tender for full passenger + ramp.
A41: Spain | B41: Vitoria | C41: Vitoria Airport | D41: LEVT | E41: VIT | F41: WFS Vitoria | G41: Handler | H41: Cargo freighter ramp | I41: WFS | J41: Not disclosed | K41: Mixed | L41: Freighter-only ramp handling — cargo-focused station.
A42: Spain | B42: Menorca | C42: Menorca Airport | D42: LEMH | E42: MAH | F42: Aviapartner Menorca | G42: Handler | H42: Commercial | I42: Aviapartner | J42: Part of ~12,000 | K42: Mixed
A43: Spain | B43: Tenerife | C43: Tenerife South | D43: GCTS | E43: TFS | F43: Groundforce Tenerife | G43: Handler | H43: Commercial | I43: Globalia | J43: Part of group | K43: Traditional | L43: Canaries are heavily charter/ULCC — high-volume, lean-margin, strong operational-tooling fit.
A44: Italy | B44: Milan | C44: Milan Malpensa | D44: LIMC | E44: MXP | F44: Airport Handling S.p.A. | G44: Handler | H44: Commercial | I44: dnata (now integrated under dnata brand, Nov 2025) | J44: ~2,500+ | K44: Mixed | L44: Previously independent, now part of dnata Italy consolidation. In transition — may be inheriting dnata tools, but integration noise = opportunity for point solutions.
A45: Italy | B45: Milan | C45: Milan Malpensa | D45: LIMC | E45: MXP | F45: GH Italia (Malpensa station) | G45: Handler | H45: Commercial | I45: Alisud Group (private, independent) | J45: Not disclosed per station | K45: Traditional | L45: Largest Italian independent. Covers ~11 Italian airports + LHR. Flagship independent prospect.
A46: Italy | B46: Milan | C46: Milan Linate | D46: LIML | E46: LIN | F46: Universal Aviation Milan | G46: FBO supervisory | H46: Biz Av | I46: Universal Weather (US parent) | J46: Not disclosed | K46: Modern | L46: Biz-av supervisory agent. First company in Italy dedicated to GA/biz av. IS-BAH certified.
A47: Italy | B47: Rome | C47: Rome Fiumicino | D47: LIRF | E47: FCO | F47: GH Italia Fiumicino | G47: Handler | H47: Commercial | I47: Alisud | J47: Not disclosed | K47: Traditional
A48: Italy | B48: Rome | C48: Rome Ciampino | D48: LIRA | E48: CIA | F48: GH Italia Ciampino | G48: Handler + biz-av | H48: Mixed | I48: Alisud | J48: Not disclosed | K48: Traditional | L48: CIA is Rome's biz-av hub — mixed traffic including heavy private/charter.
A49: Italy | B49: Rome | C49: Rome Ciampino | D49: LIRA | E49: CIA | F49: Universal Aviation Rome | G49: FBO supervisory | H49: Biz Av | I49: Universal Weather | J49: Not disclosed | K49: Modern | L49: IS-BAH certified.
A50: Italy | B50: Venice | C50: Venice Marco Polo | D50: LIPZ | E50: VCE | F50: GH Italia Venice | G50: Handler | H50: Commercial | I50: Alisud | J50: Not disclosed | K50: Traditional
A51: Italy | B51: Venice | C51: Venice Marco Polo | D51: LIPZ | E51: VCE | F51: Universal Aviation Venice | G51: FBO supervisory | H51: Biz Av | I51: Universal Weather | J51: Not disclosed | K51: Modern
A52: Italy | B52: Naples | C52: Naples Capodichino | D52: LIRN | E52: NAP | F52: GH Italia Naples | G52: Handler | H52: Commercial | I52: Alisud | J52: Not disclosed | K52: Traditional | L52: Alisud's home base — origin of the GH Italia spin-off.
A53: Italy | B53: Verona | C53: Verona Villafranca | D53: LIPX | E53: VRN | F53: GH Italia Verona | G53: Handler | H53: Commercial | I53: Alisud | J53: Not disclosed | K53: Traditional
A54: Italy | B54: Florence | C54: Florence Peretola | D54: LIRQ | E54: FLR | F54: GH Italia Florence | G54: Handler | H54: Commercial | I54: Alisud | J54: Not disclosed | K54: Traditional
A55: Italy | B55: Palermo | C55: Palermo Falcone-Borsellino | D55: LICJ | E55: PMO | F55: GH Italia Palermo | G55: Handler | H55: Commercial | I55: Alisud | J55: Not disclosed | K55: Traditional
A56: Italy | B56: Catania | C56: Catania Fontanarossa | D56: LICC | E56: CTA | F56: GH Italia Catania | G56: Handler | H56: Commercial | I56: Alisud | J56: Not disclosed | K56: Traditional
A57: Italy | B57: Bologna | C57: Bologna Borgo Panigale | D57: LIPE | E57: BLQ | F57: GH Italia Bologna | G57: Handler | H57: Commercial | I57: Alisud | J57: Not disclosed | K57: Traditional
A58: Italy | B58: Cagliari | C58: Cagliari Elmas | D58: LIEE | E58: CAG | F58: GH Italia Cagliari | G58: Handler | H58: Commercial | I58: Alisud | J58: Not disclosed | K58: Traditional
A59: Italy | B59: Bari | C59: Bari Karol Wojtyła | D59: LIBD | E59: BRI | F59: GH Italia Bari | G59: Handler | H59: Commercial | I59: Alisud | J59: Not disclosed | K59: Traditional
A60: Italy | B60: Brindisi | C60: Brindisi Salento | D60: LIBR | E60: BDS | F60: GH Italia Brindisi | G60: Handler | H60: Commercial | I60: Alisud | J60: Not disclosed | K60: Traditional
A61: Italy | B61: Cuneo (Turin area) | C61: Cuneo-Levaldigi | D61: LIMZ | E61: CUF | F61: Sky Valet Connect Cuneo | G61: FBO | H61: Biz Av | I61: Sky Valet Connect franchise (independent) | J61: Not disclosed | K61: Modern | L61: First Sky Valet Connect member — independent FBO using the ACA brand.
A62: France | B62: Paris | C62: Paris–Le Bourget | D62: LFPB | E62: LBG | F62: Sky Valet Paris-Le Bourget | G62: FBO | H62: Biz Av | I62: Luxaviation (acquired from ACA 2020) | J62: Not disclosed | K62: Modern | L62: Europe's #1 biz-av airport. ~6,000 movements/yr under ACA; ~12% share at acquisition. Now part of Luxaviation ExecuJet network.
A63: France | B63: Paris | C63: Paris–Le Bourget | D63: LFPB | E63: LBG | F63: Advanced Air Support (AAS) | G63: Handler | H63: Biz Av | I63: Sky Valet Connect franchise (independent) | J63: Not disclosed | K63: Mixed | L63: ~15% of Le Bourget private aviation traffic. Joined Sky Valet Connect — kept independence, manages own equipment fleet. STRONG INDEPENDENT PROSPECT.
A64: France | B64: Paris | C64: Paris–Le Bourget | D64: LFPB | E64: LBG | F64: Jetex Le Bourget | G64: FBO | H64: Biz Av | I64: Jetex (UAE) | J64: Not disclosed | K64: Modern | L64: Five-star rated FBO.
A65: France | B65: Nice | C65: Nice Côte d'Azur | D65: LFMN | E65: NCE | F65: Aviapartner Nice | G65: Handler | H65: Commercial | I65: Aviapartner | J65: Part of ~12,000 | K65: Mixed
A66: France | B66: Cannes | C66: Cannes-Mandelieu | D66: LFMD | E66: CEQ | F66: Sky Valet Cannes Mandelieu | G66: FBO | H66: Biz Av | I66: ACA | J66: Not disclosed | K66: Modern | L66: Sky Valet flagship. Film Festival + Monaco GP peaks. Highly digital.
A67: France | B67: Saint-Tropez | C67: Golfe de Saint-Tropez (La Môle) | D67: LFTZ | E67: LTT | F67: Sky Valet Saint-Tropez | G67: FBO | H67: Biz Av | I67: ACA | J67: Not disclosed | K67: Modern
A68: France | B68: Avignon | C68: Avignon-Provence | D68: LFMV | E68: AVN | F68: Sky Valet Avignon | G68: FBO | H68: Biz Av | I68: ACA | J68: Not disclosed | K68: Modern
A69: France | B69: Biarritz | C69: Biarritz-Pays Basque | D69: LFBZ | E69: BIQ | F69: Sky Valet Biarritz | G69: FBO | H69: Biz Av | I69: ACA | J69: Not disclosed | K69: Modern
A70: France | B70: Caen | C70: Caen-Carpiquet | D70: LFRK | E70: CFR | F70: Sky Valet Caen | G70: FBO | H70: Biz Av | I70: ACA | J70: Not disclosed | K70: Modern
A71: France | B71: Courchevel | C71: Courchevel Altiport | D71: LFLJ | E71: CVF | F71: Sky Valet Courchevel | G71: FBO seasonal | H71: Biz Av | I71: ACA | J71: Small seasonal team | K71: Modern | L71: Winter-only altiport. Highly seasonal op — good case for lightweight saas.
A72: France | B72: Deauville | C72: Deauville-Normandie | D72: LFRG | E72: DOL | F72: Sky Valet Deauville | G72: FBO | H72: Biz Av | I72: ACA | J72: Not disclosed | K72: Modern
A73: France | B73: Quimper | C73: Quimper Bretagne | D73: LFRQ | E73: UIP | F73: Sky Valet Quimper | G73: FBO | H73: Biz Av | I73: ACA | J73: Not disclosed | K73: Modern
A74: France | B74: Rodez | C74: Rodez-Aveyron | D74: LFCR | E74: RDZ | F74: Sky Valet Rodez | G74: FBO | H74: Biz Av | I74: ACA | J74: Not disclosed | K74: Modern
A75: France | B75: Saint-Étienne | C75: Saint-Étienne-Loire | D75: LFMH | E75: EBU | F75: Sky Valet Saint-Étienne | G75: FBO | H75: Biz Av | I75: ACA | J75: Not disclosed | K75: Modern
A76: France | B76: Marseille | C76: Marseille-Provence | D76: LFML | E76: MRS | F76: Aviapartner Marseille | G76: Handler | H76: Commercial | I76: Aviapartner | J76: Part of ~12,000 | K76: Mixed
A77: France | B77: Marseille | C77: Marseille-Provence | D77: LFML | E77: MRS | F77: Jetex Marseille | G77: FBO | H77: Biz Av | I77: Jetex | J77: Not disclosed | K77: Modern
A78: France | B78: Toulouse | C78: Toulouse-Blagnac | D78: LFBO | E78: TLS | F78: Aviapartner Toulouse | G78: Handler | H78: Commercial | I78: Aviapartner | J78: Part of ~12,000 | K78: Mixed
A79: France | B79: Toulouse | C79: Toulouse-Blagnac | D79: LFBO | E79: TLS | F79: Jetex Toulouse | G79: FBO | H79: Biz Av | I79: Jetex | J79: Not disclosed | K79: Modern
A80: France | B80: Bordeaux | C80: Bordeaux-Mérignac | D80: LFBD | E80: BOD | F80: Aviapartner Bordeaux | G80: Handler | H80: Commercial | I80: Aviapartner | J80: Part of ~12,000 | K80: Mixed | L80: Acquired from SAT Bordeaux in 2010. Also covers La Rochelle.
A81: France | B81: La Rochelle | C81: La Rochelle-Île de Ré | D81: LFBH | E81: LRH | F81: Aviapartner La Rochelle | G81: Handler | H81: Commercial | I81: Aviapartner | J81: Small station | K81: Mixed
A82: France | B82: Chambéry | C82: Chambéry-Savoie | D82: LFLB | E82: CMF | F82: Airport operator handling | G82: Handler | H82: Mixed | I82: Chambéry Airport SA | J82: Not disclosed | K82: Traditional | L82: Winter-slot-coordinated. Ski-season crunch — huge turn-volume for ~14 weeks.
A83: France | B83: Annecy | C83: Annecy-Haute-Savoie | D83: LFLP | E83: NCY | F83: Airport operator handling | G83: Handler | H83: Mixed | I83: Annecy Airport | J83: Small | K83: Traditional | L83: Winter-slot-coordinated.
A84: Germany | B84: Hannover | C84: Hannover Airport | D84: EDDV | E84: HAJ | F84: AHS Hannover | G84: Handler | H84: Commercial | I84: AHS Aviation Handling Services (independent) | J84: Not disclosed (~21,000 flights/yr, 2.1M pax in 2017) | K84: Traditional | L84: AHS is THE largest German independent handler — serves HAJ, DUS, HAM, STR (via SGS), BRE, NUE partner. Clear dashboard prospect.
A85: Germany | B85: Düsseldorf | C85: Düsseldorf Airport | D85: EDDL | E85: DUS | F85: AHS Düsseldorf + AHS EuroGround | G85: Handler | H85: Commercial | I85: AHS | J85: ~82,000 flights, 9.5M pax in 2017 | K85: Traditional | L85: Handling Condor, Emirates, Eurowings, Swiss, TK, Tuifly, ANA, Delta and more. Major operation.
A86: Germany | B86: Hamburg | C86: Hamburg Airport | D86: EDDH | E86: HAM | F86: AHS Hamburg | G86: Handler | H86: Commercial | I86: AHS | J86: Not disclosed | K86: Traditional | L86: Austrian, Condor, Emirates, Ryanair, Swiss, Tuifly, Turkish + more.
A87: Germany | B87: Stuttgart | C87: Stuttgart Airport | D87: EDDS | E87: STR | F87: SGS Stuttgart Ground Services | G87: Handler | H87: Commercial | I87: 49% AHS / 51% airport (FSG) | J87: Not disclosed | K87: Traditional | L87: JV structure common in DE — both parent groups could influence tool choice.
A88: Germany | B88: Stuttgart | C88: Stuttgart Airport | D88: EDDS | E88: STR | F88: Kurz Aviation Service (KAS) | G88: FBO | H88: Biz Av | I88: Kurz Aviation Group (independent) | J88: Not disclosed | K88: Modern | L88: 25+ yr experience. Partner with ExecuJet + Jet Aviation + Air Elite network. Operates BAC Frankfurt + BAC Cologne too.
A89: Germany | B89: Nuremberg | C89: Nuremberg Airport | D89: EDDN | E89: NUE | F89: AirPart Nuremberg | G89: Handler | H89: Commercial | I89: Nuremberg Airport (owns 1% of AHS) | J89: Not disclosed | K89: Traditional | L89: Airport-owned handler. Local marketing partner for AHS.
A90: Germany | B90: Bremen | C90: Bremen Airport | D90: EDDW | E90: BRE | F90: AHS Bremen | G90: Handler | H90: Commercial | I90: AHS | J90: Small station | K90: Traditional | L90: Air France, KLM Cityhopper, Lufthansa, Ryanair, Turkish.
A91: Germany | B91: Leipzig | C91: Leipzig/Halle Airport | D91: EDDP | E91: LEJ | F91: ASL Airport Services Leipzig | G91: Handler | H91: Commercial | I91: Independent, AHS partner | J91: Not disclosed | K91: Traditional | L91: Leading handler at LEJ. P&O for Lufthansa + others. Major DHL cargo hub.
A92: Germany | B92: Dresden | C92: Dresden Airport | D92: EDDC | E92: DRS | F92: ASD Airport Services Dresden | G92: Handler | H92: Commercial | I92: Independent, AHS partner | J92: Not disclosed | K92: Traditional
A93: Germany | B93: Frankfurt | C93: Frankfurt am Main | D93: EDDF | E93: FRA | F93: Business Aviation Centre Frankfurt (BAC) | G93: FBO | H93: Biz Av | I93: Kurz Aviation Group | J93: Not disclosed | K93: Modern | L93: ExecuJet + Jet Aviation + Air Elite partner. Modern biz-av FBO.
A94: Germany | B94: Cologne | C94: Cologne/Bonn Airport | D94: EDDK | E94: CGN | F94: Business Aviation Centre Cologne | G94: FBO | H94: Biz Av | I94: Kurz Aviation Group | J94: Not disclosed | K94: Modern
A95: Portugal | B95: Lisbon | C95: Humberto Delgado (Lisbon) | D95: LPPT | E95: LIS | F95: Portway | G95: Handler + FBO | H95: Commercial + Biz Av | I95: ANA Aeroportos de Portugal (Vinci) | J95: ~1,600 | K95: Mixed | L95: THE national Portuguese handler. 80+ airline clients. IATA CBTA certified, IQF training certified. Revenue ~$86.5M. Vinci Airports ownership may centralise tooling decisions.
A96: Portugal | B96: Porto | C96: Porto (Sá Carneiro) | D96: LPPR | E96: OPO | F96: Portway Porto | G96: Handler | H96: Commercial | I96: ANA/Vinci | J96: Part of ~1,600 | K96: Mixed
A97: Portugal | B97: Porto | C97: Porto (Sá Carneiro) | D97: LPPR | E97: OPO | F97: Sky Valet Porto | G97: FBO | H97: Biz Av | I97: ACA | J97: Not disclosed | K97: Modern
A98: Portugal | B98: Faro | C98: Faro Airport | D98: LPFR | E98: FAO | F98: Portway Faro | G98: Handler | H98: Commercial | I98: ANA/Vinci | J98: Part of ~1,600 | K98: Mixed | L98: Heavy seasonal charter — Algarve summer peak.
A99: Portugal | B99: Faro | C99: Faro Airport | D99: LPFR | E99: FAO | F99: Sky Valet Faro | G99: FBO | H99: Biz Av | I99: ACA | J99: Not disclosed | K99: Modern
A100: Portugal | B100: Funchal | C100: Madeira Airport | D100: LPMA | E100: FNC | F100: Portway Funchal | G100: Handler | H100: Commercial | I100: ANA/Vinci | J100: Part of ~1,600 | K100: Mixed
...

Sheet Summary by Country
A1: Country rollup
A2: Country | B2: Total operators listed | C2: Modern | D2: Mixed | E2: Traditional
A3: Spain | B3: =COUNTIF('FBO & Handler Directory'!A:A,A3) -> 42 | C3: =COUNTIFS('FBO & Handler Directory'!A:A,A3,'FBO & Handler Directory'!K:K,"Modern") -> 25 | D3: =COUNTIFS('FBO & Handler Directory'!A:A,A3,'FBO & Handler Directory'!K:K,"Mixed") -> 15 | E3: =COUNTIFS('FBO & Handler Directory'!A:A,A3,'FBO & Handler Directory'!K:K,"Traditional") -> 2
A4: Italy | B4: =COUNTIF('FBO & Handler Directory'!A:A,A4) -> 18 | C4: =COUNTIFS('FBO & Handler Directory'!A:A,A4,'FBO & Handler Directory'!K:K,"Modern") -> 4 | D4: =COUNTIFS('FBO & Handler Directory'!A:A,A4,'FBO & Handler Directory'!K:K,"Mixed") -> 1 | E4: =COUNTIFS('FBO & Handler Directory'!A:A,A4,'FBO & Handler Directory'!K:K,"Traditional") -> 13
A5: France | B5: =COUNTIF('FBO & Handler Directory'!A:A,A5) -> 22 | C5: =COUNTIFS('FBO & Handler Directory'!A:A,A5,'FBO & Handler Directory'!K:K,"Modern") -> 14 | D5: =COUNTIFS('FBO & Handler Directory'!A:A,A5,'FBO & Handler Directory'!K:K,"Mixed") -> 6 | E5: =COUNTIFS('FBO & Handler Directory'!A:A,A5,'FBO & Handler Directory'!K:K,"Traditional") -> 2
A6: Germany | B6: =COUNTIF('FBO & Handler Directory'!A:A,A6) -> 11 | C6: =COUNTIFS('FBO & Handler Directory'!A:A,A6,'FBO & Handler Directory'!K:K,"Modern") -> 3 | D6: =COUNTIFS('FBO & Handler Directory'!A:A,A6,'FBO & Handler Directory'!K:K,"Mixed") -> 0 | E6: =COUNTIFS('FBO & Handler Directory'!A:A,A6,'FBO & Handler Directory'!K:K,"Traditional") -> 8
A7: Portugal | B7: =COUNTIF('FBO & Handler Directory'!A:A,A7) -> 12 | C7: =COUNTIFS('FBO & Handler Directory'!A:A,A7,'FBO & Handler Directory'!K:K,"Modern") -> 7 | D7: =COUNTIFS('FBO & Handler Directory'!A:A,A7,'FBO & Handler Directory'!K:K,"Mixed") -> 5 | E7: =COUNTIFS('FBO & Handler Directory'!A:A,A7,'FBO & Handler Directory'!K:K,"Traditional") -> 0
A8: Greece | B8: =COUNTIF('FBO & Handler Directory'!A:A,A8) -> 13 | C8: =COUNTIFS('FBO & Handler Directory'!A:A,A8,'FBO & Handler Directory'!K:K,"Modern") -> 3 | D8: =COUNTIFS('FBO & Handler Directory'!A:A,A8,'FBO & Handler Directory'!K:K,"Mixed") -> 10 | E8: =COUNTIFS('FBO & Handler Directory'!A:A,A8,'FBO & Handler Directory'!K:K,"Traditional") -> 0
A9: UK | B9: =COUNTIF('FBO & Handler Directory'!A:A,A9) -> 6 | C9: =COUNTIFS('FBO & Handler Directory'!A:A,A9,'FBO & Handler Directory'!K:K,"Modern") -> 1 | D9: =COUNTIFS('FBO & Handler Directory'!A:A,A9,'FBO & Handler Directory'!K:K,"Mixed") -> 5 | E9: =COUNTIFS('FBO & Handler Directory'!A:A,A9,'FBO & Handler Directory'!K:K,"Traditional") -> 0
A10: Denmark | B10: =COUNTIF('FBO & Handler Directory'!A:A,A10) -> 2 | C10: =COUNTIFS('FBO & Handler Directory'!A:A,A10,'FBO & Handler Directory'!K:K,"Modern") -> 1 | D10: =COUNTIFS('FBO & Handler Directory'!A:A,A10,'FBO & Handler Directory'!K:K,"Mixed") -> 1 | E10: =COUNTIFS('FBO & Handler Directory'!A:A,A10,'FBO & Handler Directory'!K:K,"Traditional") -> 0
A11: Sweden | B11: =COUNTIF('FBO & Handler Directory'!A:A,A11) -> 4 | C11: =COUNTIFS('FBO & Handler Directory'!A:A,A11,'FBO & Handler Directory'!K:K,"Modern") -> 3 | D11: =COUNTIFS('FBO & Handler Directory'!A:A,A11,'FBO & Handler Directory'!K:K,"Mixed") -> 1 | E11: =COUNTIFS('FBO & Handler Directory'!A:A,A11,'FBO & Handler Directory'!K:K,"Traditional") -> 0
A12: Norway | B12: =COUNTIF('FBO & Handler Directory'!A:A,A12) -> 5 | C12: =COUNTIFS('FBO & Handler Directory'!A:A,A12,'FBO & Handler Directory'!K:K,"Modern") -> 4 | D12: =COUNTIFS('FBO & Handler Directory'!A:A,A12,'FBO & Handler Directory'!K:K,"Mixed") -> 1 | E12: =COUNTIFS('FBO & Handler Directory'!A:A,A12,'FBO & Handler Directory'!K:K,"Traditional") -> 0
A13: Finland | B13: =COUNTIF('FBO & Handler Directory'!A:A,A13) -> 1 | C13: =COUNTIFS('FBO & Handler Directory'!A:A,A13,'FBO & Handler Directory'!K:K,"Modern") -> 1 | D13: =COUNTIFS('FBO & Handler Directory'!A:A,A13,'FBO & Handler Directory'!K:K,"Mixed") -> 0 | E13: =COUNTIFS('FBO & Handler Directory'!A:A,A13,'FBO & Handler Directory'!K:K,"Traditional") -> 0
A14: Belgium | B14: =COUNTIF('FBO & Handler Directory'!A:A,A14) -> 4 | C14: =COUNTIFS('FBO & Handler Directory'!A:A,A14,'FBO & Handler Directory'!K:K,"Modern") -> 0 | D14: =COUNTIFS('FBO & Handler Directory'!A:A,A14,'FBO & Handler Directory'!K:K,"Mixed") -> 4 | E14: =COUNTIFS('FBO & Handler Directory'!A:A,A14,'FBO & Handler Directory'!K:K,"Traditional") -> 0
... A23: Malta | B23: =COUNTIF('FBO & Handler Directory'!A:A,A23) -> 1 | C23: =COUNTIFS('FBO & Handler Directory'!A:A,A23,'FBO & Handler Directory'!K:K,"Modern") -> 0 | D23: =COUNTIFS('FBO & Handler Directory'!A:A,A23,'FBO & Handler Directory'!K:K,"Mixed") -> 1 | E23: =COUNTIFS('FBO & Handler Directory'!A:A,A23,'FBO & Handler Directory'!K:K,"Traditional") -> 0
A24: TOTAL | B24: =SUM(B3:B23) -> 164 | C24: =SUM(C3:C23) -> 76 | D24: =SUM(D3:D23) -> 57 | E24: =SUM(E3:E23) -> 31

Sheet Top prospects shortlist
A1: High-signal prospects for a flight-ops dashboard
A2: Criteria: (1) independent or loose network, (2) multi-station ops (pain of coordination), (3) not already using a global parent's internal system, (4) recent investment or growth signal = budget + attention.
A3: Company | B3: Country | C3: Why it's a strong fit | D3: Suggested opening angle
A4: General Aviation Service (G.A.S.) | B4: Spain | C4: 9 Spanish FBO bases, ~100 staff, actively investing in new equipment (€200k in early 2025, TowFLEXX deployment). Multi-station coordination pain. Family-owned — decisions fast. | D4: Congratulate on TowFLEXX deployment in Alicante. Ask how they coordinate turn progress + equipment across 9 bases today — is it WhatsApp + email?
A5: GH Italia (Alisud) | B5: Italy | C5: 11+ Italian stations + LHR. Largest Italian independent. Recently under pressure from dnata consolidating Airport Handling SpA. | D5: Frame: 'while dnata integrates, you are the biggest truly Italian independent — want to stay that way long-term? Here's how an ops layer protects that.'
A6: Goldair Handling | B6: Greece | C6: Already ISO 27001 certified — CISO buys security claims easily. 160+ airline customers. Network: GR + CY + BG + IN + RS. 177k flights/yr. | D6: Lean on the ISO 27001 angle. They clearly value information-security sophistication. Show how dashboard audit trails + RBAC help the next recert.
A7: Skyserv Handling Services | B7: Greece | C7: 37 Greek airports — that is an enormous station-count for a single ops team to monitor. Island + seasonality variance makes real-time visibility valuable. | D7: Seasonality angle: 'how do your Mykonos, Santorini, Heraklion station managers share situational awareness in August peak?'
A8: Aviator (Nordic) | B8: Denmark / Nordics | C8: Largest independent handler in Nordics. 15 airports across 4 countries. Recently renewed + expanded AF-KL contract, signalling growth + reinvestment. | D8: The AF-KL renewal is fresh. Ask what they committed to the airline on ops visibility / on-time metrics — dashboard can deliver those SLAs.
A9: AHS Aviation Handling Services | B9: Germany | C9: Largest German independent — HAJ, DUS, HAM, STR (SGS JV), BRE, NUE (AirPart), LEJ (ASL partner), DRS (ASD partner). Clear traditional posture. Huge upside. | D9: Straight pitch: 'you're the biggest independent in Germany but your JV + partner structure means your data lives in 6 different places. Unify it.'
A10: Portway | B10: Portugal | C10: Vinci Airports subsidiary (via ANA). 1,600 employees, 5 Portuguese airports, 80+ airlines. Cargo-award heavy. Vinci will push digitisation across airports — perfect tailwind. | D10: The Vinci angle: 'other Vinci airports (e.g., London Gatwick) use modern digital ops tools — can support internal comparability pitch to ANA board.'
A11: Mallorcair | B11: Spain | C11: Just won Palma's FBO1 executive terminal contract. EMEA Top 10 FBO. Strong local brand. Island isolation = logistics complexity they already manage well. | D11: Congratulate on FBO1 award. Ask about their ops planning pre-summer peak — June to September is ~half their annual volume.
A12: Advanced Air Support (AAS) | B12: France | C12: ~15% private-av share at Le Bourget. Kept independence by joining Sky Valet Connect, so clearly values autonomy. Big equipment fleet. | D12: Autonomy angle: 'you joined Sky Valet Connect to get the brand, not the tools — the tools should be your own choice.'
A13: Advantage Flight Support (AFSL) | B13: UK | C13: Small independent biz-av FBO at EMA with supervisory network across multiple UK airports. Services LTN, STN, LBA, DSA, BHX, MAN, GLA. | D13: Multi-station supervisory pain — a single pane to track aircraft across 7 airports is exactly the problem.
A14: Euro Jet Intercontinental | B14: Czechia / Eastern Europe | C14: Prague HQ, ~200+ staff, agents in 29 countries + representation in 52 more. Ops complexity is their USP. Tech-forward. | D14: They already think in terms of coordination-across-borders. Ask what tool they use internally to keep 29-country network visible day-to-day.
... A18: Kurz Aviation Group | B18: Germany | C18: Operates STR (KAS), Cologne + Frankfurt (BAC). 25+ yr brand. Partner with ExecuJet + Jet Aviation + Air Elite — already in high-service segment. | D18: Premium-service angle: 'your customers (ExecuJet clients etc.) expect visibility; your competitors in biz-av all have dashboards; here's yours.'
